dead.py
dead-2.0.1.dist-info/LICENSE
dead-2.0.1.dist-info/METADATA
dead-2.0.1.dist-info/WHEEL
dead-2.0.1.dist-info/entry_points.txt
dead-2.0.1.dist-info/top_level.txt
dead-2.0.1.dist-info/RECORD
